{"dependencies":[{"name":"/Users/donhamiltoniii/Documents/personal-projects/javascript-projects/getting-started-with-hyperapp-and-parcel/.babelrc","includedInParent":true,"mtime":1522855700407},{"name":"/Users/donhamiltoniii/Documents/personal-projects/javascript-projects/getting-started-with-hyperapp-and-parcel/package.json","includedInParent":true,"mtime":1522858169935},{"name":"hyperapp","loc":{"line":1,"column":23}},{"name":"debounce-promise","loc":{"line":2,"column":21}},{"name":"./src/app/Header","loc":{"line":4,"column":19}},{"name":"./src/app/Footer","loc":{"line":5,"column":19}},{"name":"./src/app/Main","loc":{"line":6,"column":17}},{"name":"./public/css/style.css","loc":{"line":8,"column":7}}],"generated":{"js":"'use strict';\n\nvar _hyperapp = require('hyperapp');\n\nvar _debouncePromise = require('debounce-promise');\n\nvar _debouncePromise2 = _interopRequireDefault(_debouncePromise);\n\nvar _Header = require('./src/app/Header');\n\nvar _Header2 = _interopRequireDefault(_Header);\n\nvar _Footer = require('./src/app/Footer');\n\nvar _Footer2 = _interopRequireDefault(_Footer);\n\nvar _Main = require('./src/app/Main');\n\nvar _Main2 = _interopRequireDefault(_Main);\n\nrequire('./public/css/style.css');\n\nfunction _interopRequireDefault(obj) { return obj && obj.__esModule ? obj : { default: obj }; }\n\nvar state = {\n\tusername: '',\n\tuserData: {}\n};\n\nvar actions = {\n\tupdateUsername: function updateUsername(username) {\n\t\treturn function (state, actions) {\n\t\t\tgetUserData(username).then(actions.setUserData);\n\t\t\treturn { username: username };\n\t\t};\n\t},\n\tsetUserData: function setUserData(userData) {\n\t\treturn function (state) {\n\t\t\treturn { userData: userData };\n\t\t};\n\t}\n};\n\nvar getUserDataFn = function getUserDataFn(username) {\n\treturn fetch('https://api.github.com/users/' + username).then(function (res) {\n\t\treturn res.json();\n\t});\n};\n\nvar getUserData = (0, _debouncePromise2.default)(getUserDataFn, 700);\n\nvar view = function view(state, actions) {\n\treturn (0, _hyperapp.h)(\n\t\t'div',\n\t\t{ className: 'container' },\n\t\t(0, _hyperapp.h)(_Header2.default, null),\n\t\t(0, _hyperapp.h)(_Main2.default, { actions: actions, state: state }),\n\t\t(0, _hyperapp.h)(_Footer2.default, null)\n\t);\n};\n\n(0, _hyperapp.app)(state, actions, view, document.body);","map":{"mappings":[{"generated":{"line":3,"column":0},"source":"index.js","original":{"line":1,"column":0}},{"generated":{"line":5,"column":0},"source":"index.js","original":{"line":2,"column":0}},{"generated":{"line":9,"column":0},"source":"index.js","original":{"line":4,"column":0}},{"generated":{"line":13,"column":0},"source":"index.js","original":{"line":5,"column":0}},{"generated":{"line":17,"column":0},"source":"index.js","original":{"line":6,"column":0}},{"generated":{"line":21,"column":0},"source":"index.js","original":{"line":8,"column":0}},{"generated":{"line":25,"column":0},"source":"index.js","original":{"line":10,"column":0}},{"name":"state","generated":{"line":25,"column":4},"source":"index.js","original":{"line":10,"column":6}},{"generated":{"line":25,"column":12},"source":"index.js","original":{"line":10,"column":14}},{"name":"username","generated":{"line":26,"column":0},"source":"index.js","original":{"line":11,"column":1}},{"generated":{"line":26,"column":11},"source":"index.js","original":{"line":11,"column":11}},{"generated":{"line":26,"column":13},"source":"index.js","original":{"line":10,"column":14}},{"name":"userData","generated":{"line":27,"column":0},"source":"index.js","original":{"line":12,"column":1}},{"generated":{"line":27,"column":11},"source":"index.js","original":{"line":12,"column":11}},{"generated":{"line":28,"column":0},"source":"index.js","original":{"line":10,"column":14}},{"generated":{"line":28,"column":1},"source":"index.js","original":{"line":10,"column":0}},{"generated":{"line":30,"column":0},"source":"index.js","original":{"line":15,"column":0}},{"name":"actions","generated":{"line":30,"column":4},"source":"index.js","original":{"line":15,"column":6}},{"generated":{"line":30,"column":14},"source":"index.js","original":{"line":15,"column":16}},{"name":"updateUsername","generated":{"line":31,"column":0},"source":"index.js","original":{"line":16,"column":1}},{"generated":{"line":31,"column":17},"source":"index.js","original":{"line":16,"column":17}},{"generated":{"line":32,"column":0},"source":"index.js","original":{"line":16,"column":17}},{"generated":{"line":32,"column":9},"source":"index.js","original":{"line":16,"column":29}},{"name":"state","generated":{"line":32,"column":19},"source":"index.js","original":{"line":16,"column":30}},{"generated":{"line":32,"column":24},"source":"index.js","original":{"line":16,"column":29}},{"name":"actions","generated":{"line":32,"column":26},"source":"index.js","original":{"line":16,"column":37}},{"generated":{"line":32,"column":33},"source":"index.js","original":{"line":16,"column":29}},{"generated":{"line":32,"column":35},"source":"index.js","original":{"line":16,"column":49}},{"name":"getUserData","generated":{"line":33,"column":0},"source":"index.js","original":{"line":17,"column":2}},{"name":"username","generated":{"line":33,"column":15},"source":"index.js","original":{"line":17,"column":14}},{"generated":{"line":33,"column":23},"source":"index.js","original":{"line":17,"column":2}},{"name":"then","generated":{"line":33,"column":25},"source":"index.js","original":{"line":17,"column":24}},{"generated":{"line":33,"column":29},"source":"index.js","original":{"line":17,"column":2}},{"name":"actions","generated":{"line":33,"column":30},"source":"index.js","original":{"line":17,"column":29}},{"name":"setUserData","generated":{"line":33,"column":38},"source":"index.js","original":{"line":17,"column":37}},{"generated":{"line":33,"column":49},"source":"index.js","original":{"line":17,"column":2}},{"generated":{"line":34,"column":0},"source":"index.js","original":{"line":18,"column":2}},{"generated":{"line":34,"column":10},"source":"index.js","original":{"line":18,"column":9}},{"name":"username","generated":{"line":34,"column":12},"source":"index.js","original":{"line":18,"column":11}},{"generated":{"line":34,"column":30},"source":"index.js","original":{"line":18,"column":9}},{"generated":{"line":34,"column":32},"source":"index.js","original":{"line":18,"column":2}},{"generated":{"line":35,"column":0},"source":"index.js","original":{"line":19,"column":2}},{"generated":{"line":35,"column":3},"source":"index.js","original":{"line":16,"column":17}},{"generated":{"line":36,"column":0},"source":"index.js","original":{"line":16,"column":17}},{"generated":{"line":36,"column":2},"source":"index.js","original":{"line":15,"column":16}},{"name":"setUserData","generated":{"line":37,"column":0},"source":"index.js","original":{"line":20,"column":1}},{"generated":{"line":37,"column":14},"source":"index.js","original":{"line":20,"column":14}},{"generated":{"line":38,"column":0},"source":"index.js","original":{"line":20,"column":14}},{"generated":{"line":38,"column":9},"source":"index.js","original":{"line":20,"column":26}},{"generated":{"line":39,"column":0},"source":"index.js","original":{"line":20,"column":26}},{"generated":{"line":39,"column":10},"source":"index.js","original":{"line":20,"column":36}},{"name":"userData","generated":{"line":39,"column":12},"source":"index.js","original":{"line":20,"column":38}},{"generated":{"line":39,"column":30},"source":"index.js","original":{"line":20,"column":36}},{"generated":{"line":39,"column":32},"source":"index.js","original":{"line":20,"column":26}},{"generated":{"line":40,"column":0},"source":"index.js","original":{"line":20,"column":26}},{"generated":{"line":40,"column":3},"source":"index.js","original":{"line":20,"column":14}},{"generated":{"line":41,"column":0},"source":"index.js","original":{"line":20,"column":14}},{"generated":{"line":42,"column":0},"source":"index.js","original":{"line":15,"column":16}},{"generated":{"line":42,"column":1},"source":"index.js","original":{"line":15,"column":0}},{"generated":{"line":44,"column":0},"source":"index.js","original":{"line":23,"column":0}},{"name":"getUserDataFn","generated":{"line":44,"column":4},"source":"index.js","original":{"line":23,"column":6}},{"generated":{"line":44,"column":20},"source":"index.js","original":{"line":23,"column":22}},{"name":"getUserDataFn","generated":{"line":44,"column":29},"source":"index.js","original":{"line":23,"column":6}},{"generated":{"line":44,"column":42},"source":"index.js","original":{"line":23,"column":22}},{"generated":{"line":44,"column":53},"source":"index.js","original":{"line":23,"column":34}},{"generated":{"line":45,"column":0},"source":"index.js","original":{"line":24,"column":1}},{"name":"fetch","generated":{"line":45,"column":8},"source":"index.js","original":{"line":24,"column":8}},{"name":"username","generated":{"line":45,"column":48},"source":"index.js","original":{"line":24,"column":46}},{"generated":{"line":45,"column":56},"source":"index.js","original":{"line":24,"column":8}},{"name":"then","generated":{"line":45,"column":58},"source":"index.js","original":{"line":24,"column":58}},{"generated":{"line":45,"column":62},"source":"index.js","original":{"line":24,"column":8}},{"generated":{"line":45,"column":63},"source":"index.js","original":{"line":24,"column":63}},{"generated":{"line":46,"column":0},"source":"index.js","original":{"line":24,"column":63}},{"name":"res","generated":{"line":46,"column":9},"source":"index.js","original":{"line":25,"column":2}},{"name":"json","generated":{"line":46,"column":13},"source":"index.js","original":{"line":25,"column":6}},{"generated":{"line":46,"column":17},"source":"index.js","original":{"line":25,"column":2}},{"generated":{"line":46,"column":19},"source":"index.js","original":{"line":24,"column":63}},{"generated":{"line":47,"column":0},"source":"index.js","original":{"line":24,"column":63}},{"generated":{"line":47,"column":2},"source":"index.js","original":{"line":24,"column":8}},{"generated":{"line":47,"column":3},"source":"index.js","original":{"line":24,"column":1}},{"generated":{"line":48,"column":0},"source":"index.js","original":{"line":27,"column":1}},{"generated":{"line":48,"column":1},"source":"index.js","original":{"line":23,"column":0}},{"generated":{"line":50,"column":0},"source":"index.js","original":{"line":29,"column":0}},{"name":"getUserData","generated":{"line":50,"column":4},"source":"index.js","original":{"line":29,"column":6}},{"generated":{"line":50,"column":18},"source":"index.js","original":{"line":29,"column":20}},{"name":"getUserDataFn","generated":{"line":50,"column":49},"source":"index.js","original":{"line":29,"column":29}},{"generated":{"line":50,"column":62},"source":"index.js","original":{"line":29,"column":20}},{"generated":{"line":50,"column":64},"source":"index.js","original":{"line":29,"column":44}},{"generated":{"line":50,"column":67},"source":"index.js","original":{"line":29,"column":20}},{"generated":{"line":50,"column":68},"source":"index.js","original":{"line":29,"column":0}},{"generated":{"line":52,"column":0},"source":"index.js","original":{"line":31,"column":0}},{"name":"view","generated":{"line":52,"column":4},"source":"index.js","original":{"line":31,"column":6}},{"generated":{"line":52,"column":11},"source":"index.js","original":{"line":31,"column":13}},{"name":"view","generated":{"line":52,"column":20},"source":"index.js","original":{"line":31,"column":6}},{"generated":{"line":52,"column":24},"source":"index.js","original":{"line":31,"column":13}},{"name":"state","generated":{"line":52,"column":25},"source":"index.js","original":{"line":31,"column":14}},{"generated":{"line":52,"column":30},"source":"index.js","original":{"line":31,"column":13}},{"name":"actions","generated":{"line":52,"column":32},"source":"index.js","original":{"line":31,"column":21}},{"generated":{"line":52,"column":39},"source":"index.js","original":{"line":31,"column":13}},{"generated":{"line":53,"column":0},"source":"index.js","original":{"line":31,"column":13}},{"generated":{"line":53,"column":8},"source":"index.js","original":{"line":32,"column":1}},{"generated":{"line":54,"column":0},"source":"index.js","original":{"line":32,"column":1}},{"generated":{"line":55,"column":0},"source":"index.js","original":{"line":32,"column":1}},{"generated":{"line":55,"column":4},"source":"index.js","original":{"line":32,"column":6}},{"generated":{"line":55,"column":15},"source":"index.js","original":{"line":32,"column":16}},{"generated":{"line":55,"column":26},"source":"index.js","original":{"line":32,"column":1}},{"generated":{"line":56,"column":0},"source":"index.js","original":{"line":33,"column":2}},{"generated":{"line":56,"column":42},"source":"index.js","original":{"line":32,"column":1}},{"generated":{"line":57,"column":0},"source":"index.js","original":{"line":34,"column":2}},{"generated":{"line":57,"column":37},"source":"index.js","original":{"line":34,"column":8}},{"name":"actions","generated":{"line":57,"column":46},"source":"index.js","original":{"line":34,"column":17}},{"generated":{"line":57,"column":53},"source":"index.js","original":{"line":34,"column":2}},{"generated":{"line":57,"column":55},"source":"index.js","original":{"line":34,"column":26}},{"name":"state","generated":{"line":57,"column":62},"source":"index.js","original":{"line":34,"column":33}},{"generated":{"line":57,"column":67},"source":"index.js","original":{"line":34,"column":2}},{"generated":{"line":57,"column":70},"source":"index.js","original":{"line":32,"column":1}},{"generated":{"line":58,"column":0},"source":"index.js","original":{"line":35,"column":2}},{"generated":{"line":59,"column":0},"source":"index.js","original":{"line":32,"column":1}},{"generated":{"line":59,"column":2},"source":"index.js","original":{"line":31,"column":13}},{"generated":{"line":60,"column":0},"source":"index.js","original":{"line":31,"column":13}},{"generated":{"line":60,"column":1},"source":"index.js","original":{"line":31,"column":0}},{"generated":{"line":62,"column":0},"source":"index.js","original":{"line":39,"column":0}},{"name":"state","generated":{"line":62,"column":19},"source":"index.js","original":{"line":39,"column":4}},{"generated":{"line":62,"column":24},"source":"index.js","original":{"line":39,"column":0}},{"name":"actions","generated":{"line":62,"column":26},"source":"index.js","original":{"line":39,"column":11}},{"generated":{"line":62,"column":33},"source":"index.js","original":{"line":39,"column":0}},{"name":"view","generated":{"line":62,"column":35},"source":"index.js","original":{"line":39,"column":20}},{"generated":{"line":62,"column":39},"source":"index.js","original":{"line":39,"column":0}},{"name":"document","generated":{"line":62,"column":41},"source":"index.js","original":{"line":39,"column":26}},{"name":"body","generated":{"line":62,"column":50},"source":"index.js","original":{"line":39,"column":35}},{"generated":{"line":62,"column":54},"source":"index.js","original":{"line":39,"column":0}}],"sources":{"index.js":"import { h, app } from 'hyperapp'\nimport debounce from 'debounce-promise'\n\nimport Header from './src/app/Header'\nimport Footer from './src/app/Footer'\nimport Main from './src/app/Main'\n\nimport './public/css/style.css'\n\nconst state = {\n\tusername: '',\n\tuserData: {},\n}\n\nconst actions = {\n\tupdateUsername: username => (state, actions) => {\n\t\tgetUserData(username).then(actions.setUserData)\n\t\treturn { username }\n\t},\n\tsetUserData: userData => state => ({ userData }),\n}\n\nconst getUserDataFn = username => {\n\treturn fetch(`https://api.github.com/users/${username}`).then(res =>\n\t\tres.json(),\n\t)\n}\n\nconst getUserData = debounce(getUserDataFn, 700)\n\nconst view = (state, actions) => (\n\t<div className=\"container\">\n\t\t<Header />\n\t\t<Main actions={actions} state={state} />\n\t\t<Footer />\n\t</div>\n)\n\napp(state, actions, view, document.body)\n"},"lineCount":null}},"hash":"5333d416175a8b39db7ea5c96f729a6e","cacheData":{"env":{}}}